systembridgeconnector/__init__.py
systembridgeconnector/base.py
systembridgeconnector/const.py
systembridgeconnector/exceptions.py
systembridgeconnector/helpers.py
systembridgeconnector/http_client.py
systembridgeconnector/version.py
systembridgeconnector/websocket_client.py
systembridgeconnector/models/__init__.py
systembridgeconnector/models/action.py
systembridgeconnector/models/command_execute.py
systembridgeconnector/models/command_result.py
systembridgeconnector/models/helpers.py
systembridgeconnector/models/keyboard_key.py
systembridgeconnector/models/keyboard_text.py
systembridgeconnector/models/media_control.py
systembridgeconnector/models/media_directories.py
systembridgeconnector/models/media_files.py
systembridgeconnector/models/media_get_file.py
systembridgeconnector/models/media_get_files.py
systembridgeconnector/models/media_play.py
systembridgeconnector/models/notification.py
systembridgeconnector/models/open_path.py
systembridgeconnector/models/open_url.py
systembridgeconnector/models/request.py
systembridgeconnector/models/response.py
systembridgeconnector/models/settings.py
systembridgeconnector/models/update.py
systembridgeconnector/models/fixtures/__init__.py
systembridgeconnector/models/fixtures/media_files.py
systembridgeconnector/models/fixtures/notification.py
systembridgeconnector/models/fixtures/modules/__init__.py
systembridgeconnector/models/fixtures/modules/battery.py
systembridgeconnector/models/fixtures/modules/cpu.py
systembridgeconnector/models/fixtures/modules/disks.py
systembridgeconnector/models/fixtures/modules/displays.py
systembridgeconnector/models/fixtures/modules/gpus.py
systembridgeconnector/models/fixtures/modules/media.py
systembridgeconnector/models/fixtures/modules/memory.py
systembridgeconnector/models/fixtures/modules/networks.py
systembridgeconnector/models/fixtures/modules/processes.py
systembridgeconnector/models/fixtures/modules/sensors.py
systembridgeconnector/models/fixtures/modules/system.py
systembridgeconnector-5.3.1.dist-info/licenses/LICENSE
systembridgeconnector-5.3.1.dist-info/METADATA
systembridgeconnector-5.3.1.dist-info/WHEEL
systembridgeconnector-5.3.1.dist-info/top_level.txt
systembridgeconnector-5.3.1.dist-info/RECORD
