Metadata-Version: 2.4
Name: systembridgeconnector
Version: 5.3.1
Summary: System Bridge Connector
Home-page: https://github.com/timmo001/system-bridge-connector
Author: Aidan Timson (Timmo)
Author-email: aidan@timmo.dev
License: Apache-2.0
Keywords: system-bridge
Requires-Python: >=3.11
License-File: LICENSE
Requires-Dist: aiohttp>=3.12.15
Requires-Dist: packaging>=24.0
Dynamic: author
Dynamic: author-email
Dynamic: description
Dynamic: description-content-type
Dynamic: home-page
Dynamic: keywords
Dynamic: license
Dynamic: license-file
Dynamic: requires-dist
Dynamic: requires-python
Dynamic: summary
